{
  "Experiments": [
    {
      "ExperimentName": "Experiment One",
      "RunParallel": true,
      "RunExperiment": false,
      "PreRunData": [
        {
          "ConnectorName": "POSGRESQL",
          "ConnectorID" : "Default",
          "TestFiles": [
            "BasicTests_SetupTables"
          ]
        },
        {
          "ConnectorName": "MYSQL",
          "ConnectorID": "Default",
          "TestFiles": [
            "BasicTests_SetupTables"
          ]
        }
      ],
      "RunData": [
        {
          "ConnectorName": "POSGRESQL",
          "ConnectorID": "EquiDepth",
          "TestFiles": [
            "BasicTests_RandomNumberBlocks",
            "BasicTests_ConstantNumberBlocks"
          ]
        },
        {
          "ConnectorName": "MYSQL",
          "ConnectorID": "EquiDepth",
          "TestFiles": [
            "BasicTests_RandomNumberBlocks",
            "BasicTests_ConstantNumberBlocks"
          ]
        }
      ],
      "OptionalTestSettings": {
        "BucketSize" : 10
      }
    },
    {
      "ExperimentName": "Experiment Two",
      "RunParallel": true,
      "RunExperiment": true,
      "PreRunData": [
        {
          "ConnectorName": "POSGRESQL",
          "ConnectorID": "Default",
          "TestFiles": [
            "BasicTests_SetupTables"
          ]
        },
        {
          "ConnectorName": "MYSQL",
          "ConnectorID": "Default",
          "TestFiles": [
            "BasicTests_SetupTables"
          ]
        }
      ],
      "RunData": [
        {
          "ConnectorName": "POSGRESQL",
          "ConnectorID": "EquiDepthVariance",
          "TestFiles": [
            "BasicTests_RandomNumberBlocks",
            "BasicTests_ConstantNumberBlocks"
          ]
        },
        {
          "ConnectorName": "MYSQL",
          "ConnectorID": "EquiDepthVariance",
          "TestFiles": [
            "BasicTests_RandomNumberBlocks",
            "BasicTests_ConstantNumberBlocks"
          ]
        }
      ],
      "OptionalTestSettings": {
        "BucketSize": 10
      }
    }
  ]
}